{"stats":{"minecraft:custom":{"minecraft:jump":1409,"minecraft:time_since_rest":743,"minecraft:damage_taken":2080,"minecraft:walk_one_cm":67437,"minecraft:crouch_one_cm":4428,"minecraft:leave_game":57,"minecraft:sprint_one_cm":81048,"minecraft:play_time":60932,"minecraft:time_since_death":685,"minecraft:walk_on_water_one_cm":8599,"minecraft:deaths":9,"minecraft:sneak_time":2253,"minecraft:total_world_time":60932,"minecraft:walk_under_water_one_cm":3492,"minecraft:swim_one_cm":24059,"minecraft:fall_one_cm":80211,"minecraft:fly_one_cm":158624}},"DataVersion":3337}